infi.caching-0.0.2-py2.7-nspkg.pth
infi/caching/__init__.py
infi/caching/__version__.py
infi.caching-0.0.2.dist-info/METADATA
infi.caching-0.0.2.dist-info/WHEEL
infi.caching-0.0.2.dist-info/entry_points.txt
infi.caching-0.0.2.dist-info/namespace_packages.txt
infi.caching-0.0.2.dist-info/top_level.txt
infi.caching-0.0.2.dist-info/RECORD
